boolean_cayley_graphs/__init__.py
boolean_cayley_graphs/bent_function.py
boolean_cayley_graphs/bent_function_cayley_graph_classification.py
boolean_cayley_graphs/binary_projective_two_weight_codes.py
boolean_cayley_graphs/boolean_cayley_graph.py
boolean_cayley_graphs/boolean_function_extended_translate_classification.py
boolean_cayley_graphs/boolean_function_general_linear_class.py
boolean_cayley_graphs/boolean_function_improved.py
boolean_cayley_graphs/boolean_graph.py
boolean_cayley_graphs/boolean_linear_code.py
boolean_cayley_graphs/boolean_linear_code_graph.py
boolean_cayley_graphs/cayley_graph_controls.py
boolean_cayley_graphs/classification_database_psycopg2.py
boolean_cayley_graphs/classification_database_sqlite3.py
boolean_cayley_graphs/classify_in_mpi_parallel.py
boolean_cayley_graphs/classify_in_parallel.py
boolean_cayley_graphs/containers.py
boolean_cayley_graphs/graph_improved.py
boolean_cayley_graphs/integer_bits.py
boolean_cayley_graphs/linear.py
boolean_cayley_graphs/references.py
boolean_cayley_graphs/royle_x_graph.py
boolean_cayley_graphs/saveable.py
boolean_cayley_graphs/strongly_regular_graph.py
boolean_cayley_graphs/weight_class.py
boolean_cayley_graphs-0.2.0.dist-info/LICENSE
boolean_cayley_graphs-0.2.0.dist-info/METADATA
boolean_cayley_graphs-0.2.0.dist-info/WHEEL
boolean_cayley_graphs-0.2.0.dist-info/dependency_links.txt
boolean_cayley_graphs-0.2.0.dist-info/top_level.txt
boolean_cayley_graphs-0.2.0.dist-info/RECORD
