Metadata-Version: 2.1
Name: boolean-cayley-graphs
Version: 0.2.0
Summary: Investigations of Boolean functions, their Cayley graphs, and associated structures.
Home-page: https://github.com/penguian/Boolean-Cayley-graphs
Author: Paul Leopardi
Author-email: paul.leopardi@gmail.com
License: UNKNOWN
Platform: UNKNOWN
Classifier: Programming Language :: Python :: 3.7
Classifier: License :: OSI Approved :: GNU General Public License v3 (GPLv3)
Classifier: Operating System :: OS Independent
License-File: LICENSE
Requires-Dist: numpy
Requires-Dist: psycopg2
Requires-Dist: sagemath
